cykubedrunner/__init__.py
cykubedrunner/app.py
cykubedrunner/builder.py
cykubedrunner/common/__init__.py
cykubedrunner/common/cloudlogging.py
cykubedrunner/common/enums.py
cykubedrunner/common/exceptions.py
cykubedrunner/common/k8common.py
cykubedrunner/common/redisutils.py
cykubedrunner/common/schemas.py
cykubedrunner/common/utils.py
cykubedrunner/cypress.py
cykubedrunner/main.py
cykubedrunner/server.py
cykubedrunner/settings.py
cykubedrunner/utils.py
cykubed_runner-4.3.1.dist-info/LICENSE
cykubed_runner-4.3.1.dist-info/METADATA
cykubed_runner-4.3.1.dist-info/WHEEL
cykubed_runner-4.3.1.dist-info/entry_points.txt
cykubed_runner-4.3.1.dist-info/RECORD
