Metadata-Version: 2.1
Name: cykubed-runner
Version: 4.3.1
Summary: 
Author: support
Author-email: support@cykubed.com
Requires-Python: >=3.10,<4.0
Classifier: License :: OSI Approved :: MIT License
Classifier: Operating System :: OS Independent
Classifier: Programming Language :: Python :: 3
Classifier: Programming Language :: Python :: 3.10
Classifier: Programming Language :: Python :: 3.11
Classifier: Programming Language :: Python :: 3
Requires-Dist: aiofiles (>=23.1.0,<24.0.0)
Requires-Dist: aiohttp (>=3.8.4,<4.0.0)
Requires-Dist: aioshutil (>=1.3,<2.0)
Requires-Dist: dnspython (>=2.4.2,<3.0.0)
Requires-Dist: google-cloud-logging (>=3.5.0,<4.0.0)
Requires-Dist: httpx (>=0.24.1,<0.25.0)
Requires-Dist: loguru (>=0.6.0,<0.7.0)
Requires-Dist: pydantic (>=1.10.4,<2.0.0)
Requires-Dist: pyyaml (>=6.0,<7.0)
Requires-Dist: redis[hiredis] (==4.5.4)
Requires-Dist: sentry-sdk[httpx]
Requires-Dist: tenacity (>=8.2.2,<9.0.0)
Requires-Dist: wcmatch (>=8.4.1,<9.0.0)
